Metadata-Version: 2.1
Name: vtex
Version: 0.2.0
Summary: VTEX API Wrapper for Python
Home-page: https://github.com/lmeilibr/vtex
Author: Leandro Meili
Author-email: leandro.meili@gmail.com
License: MIT
License-File: LICENSE
Requires-Dist: requests
